tpt/__init__.py
tpt/activity.py
tpt/concatenator.py
tpt/database.py
tpt/extractor.py
tpt/file_manager.py
tpt/learner.py
tpt/request.py
tpt/statistics.py
tpt/tpt.py
tpt/commons/__init__.py
tpt/commons/act_context_enum.py
tpt/commons/cmp_result_status_enum.py
tpt/commons/cmp_type_enum.py
tpt/commons/folder_type_enum.py
tpt/commons/req_cmp_job_type_enum.py
tpt/commons/req_status_enum.py
tpt/commons/statistic_type_enum.py
tpt/commons/tpt_exception.py
tpt/comparator/__init__.py
tpt/comparator/document_checker.py
tpt/comparator/sim.py
tpt/comparator/sim_document_checker.py
tpt/comparator/tpt_comparator.py
tpt/event/__init__.py
tpt/event/event.py
tpt/event/event_handler.py
tpt/lib/sim/linux/sim_8086
tpt/lib/sim/linux/sim_c
tpt/lib/sim/linux/sim_c++
tpt/lib/sim/linux/sim_java
tpt/lib/sim/linux/sim_lisp
tpt/lib/sim/linux/sim_m2
tpt/lib/sim/linux/sim_mira
tpt/lib/sim/linux/sim_pasc
tpt/lib/sim/linux/sim_text
tpt/lib/sim/osx/TODO.txt
tpt/lib/sim/win32/sim_8086.exe
tpt/lib/sim/win32/sim_c++.exe
tpt/lib/sim/win32/sim_c.exe
tpt/lib/sim/win32/sim_java.exe
tpt/lib/sim/win32/sim_lisp.exe
tpt/lib/sim/win32/sim_m2.exe
tpt/lib/sim/win32/sim_mira.exe
tpt/lib/sim/win32/sim_pasc.exe
tpt/lib/sim/win32/sim_text.exe
tpt/model/__init__.py
tpt/model/tpt_activity.py
tpt/model/tpt_concat.py
tpt/model/tpt_concat_cmp_result.py
tpt/model/tpt_file.py
tpt/model/tpt_file_cmp_result.py
tpt/model/tpt_request.py
tpt/model/tpt_statistics.py
tpt/model/util.py
tpt/processor/__init__.py
tpt/processor/tpt_processor.py
tpt/task/__init__.py
tpt/task/analyze.py
tpt/task/compare.py
tpt/task/extract.py
tpt/task/prepare.py
tpt/task/task.py
tpt/task/update.py
tesla_ce_provider_pt_tpt_lib-1.2.dist-info/LICENSE
tesla_ce_provider_pt_tpt_lib-1.2.dist-info/METADATA
tesla_ce_provider_pt_tpt_lib-1.2.dist-info/WHEEL
tesla_ce_provider_pt_tpt_lib-1.2.dist-info/top_level.txt
tesla_ce_provider_pt_tpt_lib-1.2.dist-info/RECORD
